pyexcel_odsr/__init__.py
pyexcel_odsr/_version.py
pyexcel_odsr/messyods.py
pyexcel_odsr/odsr.py
pyexcel_odsr-0.6.0.dist-info/LICENSE
pyexcel_odsr-0.6.0.dist-info/METADATA
pyexcel_odsr-0.6.0.dist-info/WHEEL
pyexcel_odsr-0.6.0.dist-info/top_level.txt
pyexcel_odsr-0.6.0.dist-info/RECORD
