Metadata-Version: 1.2
Name: pyexcel-odsr
Version: 0.6.0
Summary: a plugin to pyexcel and provides the capbility to read data in odsformats using tailored messytables.
Home-page: https://github.com/pyexcel/pyexcel-odsr
Author: chfw
Author-email: info@pyexcel.org
License: New BSD
Download-URL: https://github.com/pyexcel/pyexcel-odsr/archive/0.6.0.tar.gz
Keywords: python,excel,ods
Platform: UNKNOWN
Classifier: Topic :: Software Development :: Libraries
Classifier: Programming Language :: Python
Classifier: Intended Audience :: Developers
Classifier: Programming Language :: Python :: 3 :: Only
Classifier: Programming Language :: Python :: 3.6
Classifier: Programming Language :: Python :: 3.7
Classifier: Programming Language :: Python :: 3.8
Classifier: License :: OSI Approved :: BSD License
Requires-Python: >=3.6
